{
    "id": "audiovisuel",
    "title": "Transport Publicité & Cinéma",
    "loader": {
        "img": ""
    },
    "componentsList": [
        {
            "id": "keydata",
            "component": "KeyDataComponent",
            "title": "Transport Publicité & Cinéma",
            "data": {
                "info": {
                    "title": "Transport Publicité & Cinéma",
                    "text": [
                        "Spécialisée dans le transport de matériel audiovisuel depuis près de 10 ans, notre équipe met tout en œuvre pour mener à bien chacun de vos projets, qu'ils soient ponctuels, récurrents, urgents ou planifiés depuis longtemps.  ",
                        "H24 Transports fait preuve d’agilité, de flexibilité et de rigueur pour s’adapter à vos besoins les plus spécifiques, de l'enlèvement à la livraison. ",
                        "Nous considérons également l'assurance, la sécurité et la confidentialité comme des priorités absolues, dans le but d’offrir un service fiable et sécurisé à nos clients."
                    ],
                    "cta": "À propos",
                    "img": "https://h24-public-website.s3.eu-west-3.amazonaws.com/assets/event/event-audiovisuel/img/cover-transport_publicity_and_cinema.jpg",
                    "link": {
                        "label": "DEMANDEZ VOTRE DEVIS",
                        "url": "#contact"
                    }
                },
                "list": [
                    {
                        "value": "1252",
                        "label": "clients satisfaits"
                    },
                    {
                        "value": "35",
                        "label": "courses réalisées"
                    },
                    {
                        "value": "2",
                        "label": "temps de trajet moyen"
                    }
                ],
                "options": {
                    "darkenBg": false
                }
            }
        },
        {
            "id": "ourvalues",
            "component": "OurValuesComponent",
            "title": "Nos Valeurs",
            "data": {
                "list": [
                    {
                        "img": "https://h24-public-website.s3.eu-west-3.amazonaws.com/assets/global/img/key-word_security.jpg",
                        "picto": "security",
                        "title": "Sécurité",
                        "text": [
                            "Nos services s’adressent à une clientèle exigeante.",
                            "H24 Transports propose des solutions de gardiennage sécurisé & vidéo-surveillé à l’intérieur même de nos locaux. Ce service vous est proposé lorsque vos départs et ou retours matériels ne sont pas réalisables dans l’immédiat."
                        ]
                    },
                    {
                        "img": "https://h24-public-website.s3.eu-west-3.amazonaws.com/assets/global/img/key-word_flexibility.jpg",
                        "picto": "timer",
                        "title": "Flexibilité",
                        "text": [
                            "Nos services sont disponibles 24h/24 et 7j/7.",
                            "Que vos besoins soient ponctuels, récurrents, urgents ou planifiés depuis longtemps, nous sommes à votre disposition. Si un imprévu survient lors d’une mission, nos équipes savent rebondir et trouver des solutions adaptées à vos contraintes d’organisation."
                        ]
                    },
                    {
                        "img": "https://h24-public-website.s3.eu-west-3.amazonaws.com/assets/global/img/key-word_optimization.jpg",
                        "picto": "settings",
                        "title": "Optimisation",
                        "text": [
                            "Conscients que les délais sont souvent courts, la logistique est au cœur de nos préoccupations. ",
                            "En étroite collaboration avec les équipes de production et les loueurs de matériel audiovisuel, nous saurons réaliser des feuilles de route afin de préparer les différentes équipes pour notre passage."
                        ]
                    },
                    {
                        "img": "https://h24-public-website.s3.eu-west-3.amazonaws.com/assets/global/img/key-word_trust.jpg",
                        "picto": "thumb_up",
                        "title": "Confiance",
                        "text": [
                            "Déjà reconnues et recommandées par les plus grands loueurs de matériel audiovisuel en Île-de-France, les équipes H24 Transports ont à cœur de respecter les délais et le matériel."
                        ]
                    }
                ],
                "options": {
                    "darkenBg": false
                }
            }
        },
        {
            "id": "delay",
            "component": "SimpleTextComponent",
            "title": "Nos délais d'intervention",
            "data": {
                "info": {
                    "title": "Nos délais d'intervention",
                    "text": [
                        "Ils sont essentiels pour garantir la qualité et la ponctualité de la production et de la diffusion des contenus. Nous devons être rapides, fiables et capables de nous adapter aux imprévus."
                    ],
                    "cta": "voir les délais",
                    "url": "/delay"
                },
                "options": {
                    "darkenBg": false
                }
            }
        },
        {
            "id": "teasingFull",
            "component": "TeasingComponent",
            "data": {
                "info": {
                    "img": "https://h24-public-website.s3.eu-west-3.amazonaws.com/assets/event/event-audiovisuel/img/full_picture-publicity_and_cinema.jpg",
                    "icon": "local_shipping",
                    "text": [
                        "Des prestations logistiques et de transport sur mesure avec des équipes professionnelles et consciencieuses."
                    ]
                },
                "options": {
                    "darkenBg": false
                }
            }
        },
        {
            "id": "ourVehicles",
            "component": "OurVehiclesComponent",
            "title": "Nos véhicules",
            "data": {
                "info": {
                    "title": "Nos véhicules"
                },
                "list": [
                    {
                        "title": "3m<sup>3</sup>",
                        "illustration": "./assets/img/camion-6-8m3.png",
                        "description": [
                            {
                                "label": "Longueur du véhicule",
                                "value": "4,5 mètres"
                            },
                            {
                                "label": "Hauteur du véhicule",
                                "value": "1,85 mètres"
                            },
                            {
                                "label": "Profondeur du coffre",
                                "value": "1,7 mètres"
                            },
                            {
                                "label": "Hauteur du coffre",
                                "value": "1,15 mètres"
                            },
                            {
                                "label": "Charge utile",
                                "value": "415 kg"
                            }
                        ]
                    },
                    {
                        "title": "6/8m<sup>3</sup>",
                        "illustration": "./assets/img/camion-6-8m3.png",
                        "description": [
                            {
                                "label": "Longueur du véhicule",
                                "value": "4,9 mètres"
                            },
                            {
                                "label": "Hauteur du véhicule",
                                "value": "1,9 mètres"
                            },
                            {
                                "label": "Profondeur du coffre",
                                "value": "2,4 mètres"
                            },
                            {
                                "label": "Hauteur du coffre",
                                "value": "1,3 mètres"
                            },
                            {
                                "label": "Charge utile",
                                "value": "820 kg"
                            }
                        ]
                    },
                    {
                        "title": "12/14m<sup>3</sup>",
                        "illustration": "./assets/img/camion-6-8m3.png",
                        "description": [
                            {
                                "label": "Longueur du véhicule",
                                "value": "6,8 mètres"
                            },
                            {
                                "label": "Hauteur du véhicule",
                                "value": "2,6 mètres"
                            },
                            {
                                "label": "Hayon",
                                "value": "inclus"
                            },
                            {
                                "label": "Profondeur du coffre",
                                "value": "4,0 mètres"
                            },
                            {
                                "label": "Hauteur du coffre",
                                "value": "1,9 mètres"
                            },
                            {
                                "label": "Charge utile",
                                "value": "1300 kg"
                            }
                        ]
                    },
                    {
                        "title": "20m<sup>3</sup>",
                        "illustration": "./assets/img/camion-6-8m3.png",
                        "description": [
                            {
                                "label": "Longueur du véhicule",
                                "value": "6,8 mètres"
                            },
                            {
                                "label": "Hauteur du véhicule",
                                "value": "3,4 mètres"
                            },
                            {
                                "label": "Hayon",
                                "value": "inclus"
                            },
                            {
                                "label": "Profondeur du coffre",
                                "value": "4,2 mètres"
                            },
                            {
                                "label": "Hauteur du coffre",
                                "value": "2,2 mètres"
                            },
                            {
                                "label": "Charge utile",
                                "value": "700 kg"
                            }
                        ]
                    }
                ],
                "options": {
                    "darkenBg": false
                }
            }
        },
        {
            "id": "client",
            "component": "ClientComponent",
            "title": "Ils nous font confiance",
            "data": {
                "info": {
                    "title": "Ils nous font confiance",
                    "imgStyle": "white",
                    "text": [
                        "H24 Transports est recommandé par de nombreux studios et loueurs de matériel audiovisuel.",
                        "Nous sommes également très fiers d’être partenaire de confiance sur des productions Netflix et Apple TV qui font appel à nos services."
                    ]
                },
                "list": [
                    {
                        "name": "Acc&Led",
                        "img": "accled.png",
                        "url": "https://www.accled.fr"
                    },
                    {
                        "name": "TSF",
                        "img": "tsf.png",
                        "url": "https://www.tsf.fr"
                    },
                    {
                        "name": "Vantage",
                        "img": "vantage.png",
                        "url": "https://www.vantagefilm.com"
                    },
                    {
                        "name": "Cininter",
                        "img": "cininter.png",
                        "url": "https://www.cininter.fr/"
                    },
                    {
                        "name": "Rouchon",
                        "img": "rouchon.png",
                        "url": "https://rouchonparis.com/"
                    },
                    {
                        "name": "Next shot",
                        "img": "nextshot.png",
                        "url": "https://www.nextshot.com/"
                    },
                    {
                        "name": "Direct Digital",
                        "img": "direct-digital.png",
                        "url": "https://www.direct-digital.com/fr-fr"
                    },
                    {
                        "name": "Little Grand Studio",
                        "img": "littlegrandstudio.png",
                        "url": "http://www.littlegrandstudio.com/Site/fr/"
                    },
                    {
                        "name": "MATphoto",
                        "img": "matphoto.png",
                        "url": "https://matphoto.fr"
                    }
                ],
                "options": {
                    "darkenBg": true
                }
            }
        },
        {
            "id": "solutions",
            "component": "InfosComponent",
            "title": "Solutions logistiques adaptées",
            "data": {
                "info": {
                    "title": "Solutions logistiques adaptées",
                    "img": "https://h24-public-website.s3.eu-west-3.amazonaws.com/assets/global/img/adapted_logistics_solutions.jpg",
                    "dropdown": [
                        {
                            "title": "Votre partenaire logistique de transport",
                            "text": [
                                "Organiser une production audiovisuelle peut être un défi logistique. Forte de son expérience, H24 Transports vous aide à respecter des délais parfois très courts avec efficacité. Nous prenons en charge toute l'organisation de la logistique des transports du matériel pour que vous puissiez vous concentrer sur votre cœur de métier."
                            ],
                            "isVisible": true
                        },
                        {
                            "title": "Collecte d'informations clés pour votre tournage",
                            "text": [
                                "En étroite collaboration avec les équipes de production ou le régisseur général, nous collectons les informations clés pour assurer le bon déroulement de votre tournage. Si nécessaire, nous pouvons mettre en place une feuille de route pour préparer notre mission et vous informer de notre passage."
                            ]
                        },
                        {
                            "title": "Solutions adaptées à la production audiovisuelle",
                            "text": [
                                "Nos équipes connaissent parfaitement les loueurs de matériel audiovisuel et les studios parisiens, avec qui nous collaborons depuis plusieurs années. Nous sommes en mesure de vous offrir des solutions logistiques adaptées à vos besoins, de l’enlèvement à la livraison avec la possibilité de stocker votre matériel en gardiennage sécurisé et vidéo-surveillé."
                            ]
                        }
                    ]
                },
                "options": {
                    "imgTo": "left",
                    "darkenBg": false
                }
            }
        },
        {
            "id": "citation1",
            "component": "CitationComponent",
            "data": {
                "info": {
                    "text": "Quels que soient vos besoins, H24 Transports s'adapte à la virgule près en vous proposant un service dédié (pas de groupage client)."
                },
                "options": {
                    "darkenBg": true
                }
            }
        },
        {
            "id": "prestations",
            "component": "InfosComponent",
            "title": "Des prestations sur mesure",
            "data": {
                "info": {
                    "title": "Des prestations sur mesure",
                    "img": "https://h24-public-website.s3.eu-west-3.amazonaws.com/assets/global/img/tailor-made_services.jpg",
                    "text": [
                        "Chez H24 Transports, nous comprenons que les imprévus peuvent survenir à tout moment. C'est pourquoi nos équipes sont réactives et disponibles pour transporter vos équipements avec efficacité.",
                        "Nous transportons caméras, machinerie, lumières, régies, costumes, collections de vêtements et tout autre matériel nécessaire à la réalisation de vos projets.",
                        "Avec notre expertise en transport, nous sommes en mesure de répondre à l'ensemble vos besoins urgents ou planifiés, tout en tenant compte de vos exigences et de vos contraintes d’organisation."
                    ]
                },
                "options": {
                    "imgTo": "right",
                    "darkenBg": false
                }
            }
        },
        {
            "id": "citation2",
            "component": "CitationComponent",
            "data": {
                "info": {
                    "text": "Des prestations logistiques et de transport sur mesure avec des équipes professionnelles et consciencieuses."
                },
                "options": {
                    "darkenBg": true
                }
            }
        },
        {
            "id": "priseEnCharge",
            "component": "InfosComponent",
            "title": "Sécurité et assurances",
            "data": {
                "info": {
                    "globalTitle": "Sécurité et assurances",
                    "title": "Une prise en charge complète",
                    "img": "https://h24-public-website.s3.eu-west-3.amazonaws.com/assets/global/img/key-word_security.jpg",
                    "text": [
                        "Nous proposons une solution complète de transport et de sécurité pour garantir la protection de votre matériel, afin que vous puissiez vous concentrer sur votre projet en toute sérénité."
                    ]
                },
                "options": {
                    "imgTo": "right",
                    "darkenBg": false
                }
            }
        },
        {
            "id": "stockage",
            "component": "InfosComponent",
            "data": {
                "info": {
                    "title": "Un stockage sécurisé",
                    "img": "https://h24-public-website.s3.eu-west-3.amazonaws.com/assets/global/img/secure_storage.jpg",
                    "text": [
                        "Nous offrons une prise en charge complète de vos besoins après le tournage, y compris le gardiennage sécurisé de nos véhicules contenant votre matériel, qui sont stockés à l'intérieur de nos locaux vidéo-surveillés et sécurisés."
                    ]
                },
                "options": {
                    "imgTo": "left",
                    "darkenBg": false
                }
            }
        },
        {
            "id": "assurance",
            "component": "InfosComponent",
            "data": {
                "info": {
                    "title": "Des assurances adaptées",
                    "img": "https://h24-public-website.s3.eu-west-3.amazonaws.com/assets/global/img/appropriate_insurance.jpg",
                    "text": [
                        "Nous avons mis en place des assurances spéciales avec des plafonds adaptés à votre secteur d'activité, pour une tranquillité d'esprit totale lors du transport de votre marchandise."
                    ]
                },
                "options": {
                    "imgTo": "right",
                    "darkenBg": false
                }
            }
        },
        {
            "id": "news",
            "component": "NewsComponent",
            "title": "Actualités",
            "data": {
                "info": {
                    "title": "Actualités"
                },
                "list": [
                    {
                        "title": "Shooting avec Emilie Couput chargé de production chez Sézane",
                        "text": [
                            "Cette prestation à été réalisée à Milan (Italie), la prod a donc souhaitée garder nos chauffeurs en presta #ManAndVan sur ce projet.",
                            "Un choix judicieux lorsque vos projets ne durent que 1, 2 ou 3 jours. Gardez nos chauffeurs qui enfilent une casquette de régisseur 'junior' sur votre set tout en impactant le moins possible votre empreinte #carbone en évitant des A-R à PARIS.",
                            "Nous tenons à remercier la marque Sézane pour la confiance accordée depuis plus d'un an."
                        ],
                        "img": "https://media.licdn.com/dms/image/C4E22AQE8mcCl6masGw/feedshare-shrink_800/0/1679059379313?e=1683763200&v=beta&t=1C8fCpsdMjD0P3Mh5VF4MWu9Xp99ia9I8HUHE4bXXy8",
                        "date": "01/02/2023"
                    },
                    {
                        "title": "Tournage pour Nike",
                        "text": [
                            "Depuis maintenant quelques années nous travaillons sur des #tournages pour Nike, toujours via des productions photos ou vidéos. Aujourd'hui nous avons l'honneur de pouvoir dire que nous travaillons en direct avec !",
                            "Un grand MERCI Mary Deville pour cette nouvelle collaboration"
                        ],
                        "img": "https://media.licdn.com/dms/image/C4E22AQESBpIh1pXbHg/feedshare-shrink_800/0/1678206579301?e=1683763200&v=beta&t=5q3_fsAzhK9hdAlbAByYquYr5Vq_xE8Vh4vEkJf6rBM",
                        "date": "01/11/2021"
                    },
                    {
                        "title": "Balenciaga",
                        "text": [
                            "Retour Matériel Balenciaga chez son loueur Vantage Film.",
                            "Merci à @titreprovisoire pour la confiance. a bientôt sur un nouvel évènement."
                        ],
                        "img": "https://media.licdn.com/dms/image/C4E22AQEUMYz8Ae9YWA/feedshare-shrink_800/0/1678092871229?e=1683763200&v=beta&t=_jLI13cnv4lg9NrCVxRYwrv3lXKPko-kLfA74t5hK00",
                        "date": "01/07/2022"
                    },
                    {
                        "title": "Show de DIOR",
                        "text": [
                            "Merci à la production Tender Night plus particulièrement à Leyla Sassi pour la confiance accordée depuis 2018.",
                            "Un plaisir de vous accompagner à chaque show de DIOR, qu'il soit Paris - Londres - Athènes."
                        ],
                        "img": "https://media.licdn.com/dms/image/C4E22AQGz0KoC2o-g5A/feedshare-shrink_800/0/1678093650541?e=1683763200&v=beta&t=BaVMrCtEr9DkFYEFxn3p5mhuPBj-YRJqxM-wlayY3fc",
                        "date": "01/01/2023"
                    }
                ],
                "options": {
                    "darkenBg": true
                }
            }
        },
        {
            "id": "contact",
            "component": "ContactComponent",
            "title": "Contactez-nous",
            "data": {
                "info": {
                    "title": "Contactez-nous",
                    "btn": "Envoyer"
                },
                "list": [
                    [
                        {
                            "name": "nom",
                            "label": "Nom",
                            "type": "text",
                            "value:": "",
                            "validators": {
                                "required": true
                            }
                        },
                        {
                            "name": "prenom",
                            "label": "Prénom",
                            "type": "text",
                            "value:": "",
                            "validators": {
                                "required": true
                            }
                        }
                    ],
                    [
                        {
                            "name": "societe",
                            "label": "Société",
                            "type": "text",
                            "value:": "",
                            "validators": {
                                "required": true
                            }
                        }
                    ],
                    [
                        {
                            "name": "email",
                            "label": "Email",
                            "type": "text",
                            "value:": "",
                            "validators": {
                                "required": true,
                                "pattern": "email"
                            }
                        }
                    ],
                    [
                        {
                            "name": "tel",
                            "label": "Téléphone",
                            "type": "text",
                            "value:": "",
                            "validators": {
                                "required": true,
                                "pattern": "phone"
                            }
                        }
                    ],
                    [
                        {
                            "name": "message",
                            "label": "Votre message",
                            "type": "textarea",
                            "value:": "",
                            "validators": {
                                "required": true,
                                "minLength": 12
                            }
                        }
                    ]
                ],
                "options": {
                    "darkenBg": false
                }
            }
        }
    ]
}
